grapl_tests_common/__init__.py
grapl_tests_common/dump_dynamodb.py
grapl_tests_common/py.typed
grapl_tests_common/setup.py
grapl_tests_common/sleep.py
grapl_tests_common/types.py
grapl_tests_common/upload_logs.py
grapl_tests_common/upload_test_data.py
grapl_tests_common/wait.py
grapl_tests_common/clients/__init__.py
grapl_tests_common/clients/engagement_edge_client.py
grapl_tests_common/clients/model_plugin_deployer_client.py
grapl_tests_common-0.0.4.dist-info/METADATA
grapl_tests_common-0.0.4.dist-info/WHEEL
grapl_tests_common-0.0.4.dist-info/namespace_packages.txt
grapl_tests_common-0.0.4.dist-info/top_level.txt
grapl_tests_common-0.0.4.dist-info/RECORD
